multiservice.py
multiservice-1.7.0.dist-info/entry_points.txt
multiservice-1.7.0.dist-info/WHEEL
multiservice-1.7.0.dist-info/METADATA
multiservice-1.7.0.dist-info/RECORD
